finalsa/traceability/__init__.py
finalsa/traceability/context.py
finalsa/traceability/functions.py
finalsa_traceability-1.0.1.dist-info/METADATA
finalsa_traceability-1.0.1.dist-info/WHEEL
finalsa_traceability-1.0.1.dist-info/licenses/LICENSE.md
finalsa_traceability-1.0.1.dist-info/RECORD
