Metadata-Version: 2.4
Name: finalsa-traceability
Version: 1.0.1
Summary: Thread-safe distributed tracing and correlation ID management for Python microservices
Project-URL: Homepage, https://github.com/finalsa/finalsa-traceability
Project-URL: Documentation, https://github.com/finalsa/finalsa-traceability#readme
Project-URL: Repository, https://github.com/finalsa/finalsa-traceability.git
Project-URL: Issues, https://github.com/finalsa/finalsa-traceability/issues
Project-URL: Changelog, https://github.com/finalsa/finalsa-traceability/blob/main/CHANGELOG.md
Author-email: Luis Jimenez <luis@finalsa.com>
License: MIT License
License-File: LICENSE.md
Keywords: async,context-management,correlation-id,distributed-tracing,finalsa,microservices,observability,thread-safe,traceability
Classifier: Development Status :: 4 - Beta
Classifier: Intended Audience :: Developers
Classifier: License :: OSI Approved :: MIT License
Classifier: Operating System :: OS Independent
Classifier: Programming Language :: Python :: 3
Classifier: Programming Language :: Python :: 3.9
Classifier: Programming Language :: Python :: 3.10
Classifier: Programming Language :: Python :: 3.11
Classifier: Programming Language :: Python :: 3.12
Classifier: Topic :: Software Development :: Libraries :: Python Modules
Classifier: Topic :: System :: Distributed Computing
Classifier: Topic :: System :: Monitoring
Classifier: Typing :: Typed
Requires-Python: >=3.9
